envjson/__init__.py
envjson/env_parser.py
envjson-20180731.1.1.dist-info/METADATA
envjson-20180731.1.1.dist-info/RECORD
envjson-20180731.1.1.dist-info/WHEEL
envjson-20180731.1.1.dist-info/top_level.txt
tests/__init__.py
tests/test_module.py
