Metadata-Version: 2.1
Name: envjson
Version: 20180731.1.1
Summary: Sample short description
Home-page: https://pypi.python.org/pypi/envjson
Author: envjson contributors
Author-email: UNKNOWN
License: BSD 3-Clause License
Platform: UNKNOWN
Classifier: Development Status :: 4 - Beta
Classifier: Operating System :: OS Independent
Classifier: Programming Language :: Python
Classifier: Programming Language :: Python :: 3
Classifier: Programming Language :: Python :: 3.7
Classifier: License :: OSI Approved :: BSD License
